vlcli
